{
  "meta": {
    "identifier": "Daemonic Icon",
    "prevIdentifier": "Plaguebringer"
  },
  "selectionEntries": [
    {
      "costs": [
        {
          "name": "pts",
          "costTypeId": "points",
          "value": 15.0
        },
        {
          "name": " PL",
          "costTypeId": "e356-c769-5920-6e14"
        }
      ],
      "constraints": [
        {
          "id": "e1bc-fc34-7490-95f1",
          "type": 1,
          "field": "selections",
          "scope": "parent",
          "value": 1.0,
          "shared": true
        }
      ],
      "id": "c081-d0eb-9152-402a",
      "name": "Daemonic Icon"
    }
  ]
}