{
  "meta": {
    "identifier": "6 Hunter-Killer Missiles",
    "prevIdentifier": "6 Skystrike Missiles"
  },
  "selectionEntries": [
    {
      "costs": [
        {
          "name": "pts",
          "costTypeId": "points",
          "value": 36.0
        },
        {
          "name": " PL",
          "costTypeId": "e356-c769-5920-6e14"
        }
      ],
      "constraints": [
        {
          "id": "3ad9-fbf1-0892-cd91",
          "type": 1,
          "field": "selections",
          "scope": "parent",
          "value": 1.0,
          "shared": true
        }
      ],
      "id": "9543-285f-8b0c-6c5a",
      "name": "6 Hunter-Killer Missiles",
      "infoLinks": [
        {
          "targetId": "e2a9-e8fc-3a6b-2eec",
          "id": "c9d3-7c3f-2715-c069",
          "name": "Hunter-killer missile"
        }
      ]
    }
  ]
}