{
  "meta": {
    "identifier": "Aggressor Sergeant"
  },
  "selectionEntries": [
    {
      "costs": [
        {
          "name": " PL",
          "costTypeId": "e356-c769-5920-6e14"
        },
        {
          "name": "pts",
          "costTypeId": "points",
          "value": 21.0
        }
      ],
      "constraints": [
        {
          "id": "a606-9e2b-6edd-1772",
          "field": "selections",
          "scope": "parent",
          "value": 1.0,
          "shared": true
        },
        {
          "id": "0116-0ddc-48df-0643",
          "type": 1,
          "field": "selections",
          "scope": "parent",
          "value": 1.0,
          "shared": true
        }
      ],
      "id": "249d-415a-7f2b-3be2",
      "name": "Aggressor Sergeant"
    }
  ]
}