{
  "meta": {
    "identifier": "Rail rifle",
    "prevIdentifier": "Quad ion turret"
  },
  "selectionEntries": [
    {
      "costs": [
        {
          "name": "pts",
          "costTypeId": "points",
          "value": 22.0
        },
        {
          "name": " PL",
          "costTypeId": "e356-c769-5920-6e14"
        }
      ],
      "collective": true,
      "id": "8bb4-d3c0-16bf-0d66",
      "name": "Rail rifle",
      "infoLinks": [
        {
          "targetId": "e5a6-bf7b-e4f1-86c1",
          "id": "02ac-a20b-66e2-6a87",
          "name": "New InfoLink"
        }
      ]
    }
  ]
}