{
  "meta": {
    "identifier": "Black Staff of Ahriman"
  },
  "selectionEntries": [
    {
      "costs": [
        {
          "name": "pts",
          "costTypeId": "points"
        },
        {
          "name": " PL",
          "costTypeId": "e356-c769-5920-6e14"
        }
      ],
      "constraints": [
        {
          "id": "aa86-e3dc-ba78-2206",
          "type": 1,
          "field": "selections",
          "scope": "parent",
          "value": 1.0,
          "shared": true
        },
        {
          "id": "e79b-fb5f-fb92-55d7",
          "field": "selections",
          "scope": "parent",
          "value": 1.0,
          "shared": true
        }
      ],
      "id": "a640-2521-08e9-fe6f",
      "name": "Black Staff of Ahriman"
    }
  ]
}