{
  "meta": {
    "identifier": "Weapons of Torture",
    "prevIdentifier": "Tools of Torment"
  },
  "selectionEntryGroups": [
    {
      "constraints": [
        {
          "id": "d4c7-d4b9-abed-513f",
          "type": 1,
          "field": "selections",
          "scope": "parent",
          "value": 1.0,
          "shared": true
        },
        {
          "id": "8d97-c11c-fe14-501d",
          "field": "selections",
          "scope": "parent",
          "shared": true
        }
      ],
      "entryLinks": [
        {
          "constraints": [
            {
              "id": "c460-8c97-a202-5e4a",
              "type": 1,
              "field": "selections",
              "scope": "parent",
              "value": 1.0,
              "shared": true
            }
          ],
          "targetId": "277e-79e0-b605-ca05",
          "id": "bd92-432d-a320-d3ee",
          "name": "New EntryLink"
        },
        {
          "constraints": [
            {
              "id": "6137-0dc8-d74e-ff0e",
              "type": 1,
              "field": "selections",
              "scope": "parent",
              "value": 1.0,
              "shared": true
            }
          ],
          "targetId": "6242-eebf-931c-e728",
          "id": "bf6b-b4c8-a199-531f",
          "name": "New EntryLink"
        },
        {
          "constraints": [
            {
              "id": "8736-ff2f-18e3-e784",
              "type": 1,
              "field": "selections",
              "scope": "parent",
              "value": 1.0,
              "shared": true
            }
          ],
          "targetId": "902e-38aa-6282-9821",
          "id": "d27e-ee32-478a-1c2f",
          "name": "New EntryLink"
        },
        {
          "constraints": [
            {
              "id": "ad2e-04bf-6fa3-ec85",
              "type": 1,
              "field": "selections",
              "scope": "parent",
              "value": 1.0,
              "shared": true
            }
          ],
          "targetId": "ae2e-c7fc-f476-ee79",
          "id": "75db-83d3-642a-088d",
          "name": "New EntryLink"
        },
        {
          "constraints": [
            {
              "id": "3d02-d64b-c06c-aaf5",
              "type": 1,
              "field": "selections",
              "scope": "parent",
              "value": 1.0,
              "shared": true
            }
          ],
          "targetId": "bac0-1ac3-c526-786e",
          "id": "0ad6-4887-9b85-b65a",
          "name": "New EntryLink"
        },
        {
          "constraints": [
            {
              "id": "ddd1-47a6-d0d0-d7e7",
              "type": 1,
              "field": "selections",
              "scope": "parent",
              "value": 1.0,
              "shared": true
            }
          ],
          "targetId": "76ac-0e9d-9553-4433",
          "id": "996b-2dff-5578-82ca",
          "name": "New EntryLink"
        }
      ],
      "id": "8df7-75dd-f85d-05c4",
      "name": "Weapons of Torture"
    }
  ]
}