{
  "meta": {
    "identifier": "DW Vet List",
    "prevIdentifier": "Deathwatch Vanguard Equipment"
  },
  "selectionEntryGroups": [
    {
      "defaultSelectionEntryId": "face-df80-e799-95f6",
      "entryLinks": [
        {
          "constraints": [
            {
              "id": "6d2a-0af2-0079-a9ac",
              "type": 1,
              "field": "selections",
              "scope": "parent",
              "value": 2.0,
              "shared": true
            }
          ],
          "targetId": "ab90-f0c3-d1cd-8494",
          "id": "7639-b12b-8cd0-b5c7",
          "name": "Bolt Pistol"
        },
        {
          "constraints": [
            {
              "id": "3654-4669-d03d-c594",
              "type": 1,
              "field": "selections",
              "scope": "parent",
              "value": 2.0,
              "shared": true
            }
          ],
          "targetId": "7b66-cac7-e582-a518",
          "id": "4ec7-90fd-ee5f-6de9",
          "name": "Grav-pistol"
        },
        {
          "constraints": [
            {
              "id": "6181-7737-f11a-bb64",
              "type": 1,
              "field": "selections",
              "scope": "parent",
              "value": 2.0,
              "shared": true
            }
          ],
          "targetId": "d1e6-5583-3104-e45b",
          "id": "7a82-c4c9-f48b-414e",
          "name": "New EntryLink"
        },
        {
          "constraints": [
            {
              "id": "0997-322f-a83f-b323",
              "type": 1,
              "field": "selections",
              "scope": "parent",
              "value": 2.0,
              "shared": true
            }
          ],
          "targetId": "83f0-56d1-b852-f21c",
          "id": "0f24-b1c9-4f15-8aff",
          "name": "New EntryLink",
          "modifiers": [
            {
              "field": "points",
              "value": "20"
            }
          ]
        },
        {
          "constraints": [
            {
              "id": "b005-4801-17ff-761a",
              "type": 1,
              "field": "selections",
              "scope": "parent",
              "value": 2.0,
              "shared": true
            }
          ],
          "targetId": "83be-1ba9-c326-4760",
          "id": "4d0e-f7b2-e334-4175",
          "name": "Plasma pistol"
        },
        {
          "constraints": [
            {
              "id": "5013-fe01-1504-096d",
              "type": 1,
              "field": "selections",
              "scope": "parent",
              "value": 2.0,
              "shared": true
            }
          ],
          "targetId": "0dd1-2e2b-7dd1-5495",
          "id": "211f-e0d1-3ed4-b68a",
          "name": "New EntryLink"
        },
        {
          "constraints": [
            {
              "id": "ee3e-afc8-3fb0-48fd",
              "type": 1,
              "field": "selections",
              "scope": "parent",
              "value": 2.0,
              "shared": true
            }
          ],
          "targetId": "90de-7b01-e401-888b",
          "id": "fbf4-f223-f5b3-de19",
          "name": "New EntryLink"
        },
        {
          "constraints": [
            {
              "id": "c3eb-705c-c1e3-e6dc",
              "type": 1,
              "field": "selections",
              "scope": "parent",
              "value": 2.0,
              "shared": true
            }
          ],
          "targetId": "3292-34e6-f679-d5b9",
          "id": "fb73-f587-9ab6-8d61",
          "name": "New EntryLink"
        },
        {
          "constraints": [
            {
              "id": "1a7c-fe8d-273f-f430",
              "type": 1,
              "field": "selections",
              "scope": "parent",
              "value": 2.0,
              "shared": true
            }
          ],
          "targetId": "f122-3720-fa32-4215",
          "id": "473f-70b4-fead-a1b3",
          "name": "New EntryLink"
        },
        {
          "constraints": [
            {
              "id": "c1ae-9a7d-d797-4286",
              "type": 1,
              "field": "selections",
              "scope": "parent",
              "value": 2.0,
              "shared": true
            }
          ],
          "targetId": "ba8d-691a-6178-1a60",
          "id": "5740-f0db-3563-7989",
          "name": "New EntryLink"
        },
        {
          "constraints": [
            {
              "id": "f684-6633-7d16-9418",
              "type": 1,
              "field": "selections",
              "scope": "parent",
              "value": 2.0,
              "shared": true
            }
          ],
          "targetId": "6ea7-1195-7144-438e",
          "id": "7e0e-e454-35da-41e6",
          "name": "New EntryLink"
        },
        {
          "constraints": [
            {
              "id": "9da1-837c-6298-547e",
              "type": 1,
              "field": "selections",
              "scope": "parent",
              "value": 2.0,
              "shared": true
            }
          ],
          "targetId": "0e57-eaf5-763f-9c45",
          "id": "ad30-ae0f-c9d3-48c1",
          "name": "New EntryLink"
        },
        {
          "constraints": [
            {
              "id": "ecd3-470a-90f9-7fb1",
              "type": 1,
              "field": "selections",
              "scope": "parent",
              "value": 2.0,
              "shared": true
            }
          ],
          "targetId": "38b5-ef30-f87f-5275",
          "id": "bf7b-f9e5-aef1-6f15",
          "name": "Storm shield"
        },
        {
          "constraints": [
            {
              "id": "b6c2-02c7-8fe6-833b",
              "type": 1,
              "field": "selections",
              "scope": "parent",
              "value": 2.0,
              "shared": true
            }
          ],
          "targetId": "bc9e-551d-9afb-78d5",
          "id": "3c6d-2962-ffc0-7fb2",
          "name": "New EntryLink"
        },
        {
          "constraints": [
            {
              "id": "20e6-c9e9-890d-ef03",
              "type": 1,
              "field": "selections",
              "scope": "parent",
              "value": 1.0,
              "shared": true
            }
          ],
          "targetId": "69ce-51e1-7d84-4eaf",
          "id": "face-df80-e799-95f6",
          "name": "Boltgun"
        },
        {
          "type": 1,
          "targetId": "6033-1f2e-cd8e-bdd0",
          "id": "a050-63eb-1939-8431",
          "name": "Or One weapon can be chosen from the following list:"
        }
      ],
      "id": "ccae-c3ab-8082-67d0",
      "name": "DW Vet List"
    }
  ]
}