{
  "meta": {
    "identifier": "Option 2"
  },
  "selectionEntryGroups": [
    {
      "defaultSelectionEntryId": "4e29-ef82-364b-75ea",
      "constraints": [
        {
          "id": "46b8-84bd-f7b5-38c2",
          "type": 1,
          "field": "selections",
          "scope": "parent",
          "value": 1.0,
          "shared": true,
          "includeChildSelections": true,
          "includeChildForces": true
        },
        {
          "id": "7cb3-8de3-8342-9c65",
          "field": "selections",
          "scope": "parent",
          "value": 1.0,
          "shared": true,
          "includeChildSelections": true,
          "includeChildForces": true
        }
      ],
      "entryLinks": [
        {
          "targetId": "2f3b-2b38-8060-efc7",
          "id": "1265-e072-0274-b19e",
          "name": "New EntryLink"
        },
        {
          "targetId": "584a-6098-3259-2249",
          "id": "4e29-ef82-364b-75ea",
          "name": "New EntryLink"
        },
        {
          "targetId": "1341-9950-38dd-6043",
          "id": "2e64-34e6-5b3e-bbf0",
          "name": "New EntryLink"
        }
      ],
      "id": "315b-1102-1c70-349c",
      "name": "Option 2"
    }
  ]
}