{
  "meta": {
    "identifier": "2 Heavy Bolters"
  },
  "selectionEntries": [
    {
      "costs": [
        {
          "name": "pts",
          "costTypeId": "points",
          "value": 16.0
        },
        {
          "name": " PL",
          "costTypeId": "e356-c769-5920-6e14"
        }
      ],
      "constraints": [
        {
          "id": "c72e-2c10-751f-80ce",
          "type": 1,
          "field": "selections",
          "scope": "parent",
          "value": 1.0,
          "shared": true
        }
      ],
      "id": "3a60-82ff-c421-6802",
      "name": "2 Heavy Bolters",
      "infoLinks": [
        {
          "targetId": "e2b0-b9f1-6c38-584c",
          "id": "d089-1dd2-2c93-efdc",
          "name": "Heavy bolter"
        }
      ]
    }
  ]
}