{
  "meta": {
    "identifier": "Ranged/melee weapons"
  },
  "selectionEntries": [
    {
      "costs": [
        {
          "name": " PL",
          "costTypeId": "e356-c769-5920-6e14"
        },
        {
          "name": "pts",
          "costTypeId": "points"
        }
      ],
      "constraints": [
        {
          "id": "8d98-cae5-1c3a-4499",
          "type": 1,
          "field": "selections",
          "scope": "parent",
          "value": 1.0,
          "shared": true
        }
      ],
      "id": "b1df-07ed-4397-0741",
      "name": "Ranged/melee weapons"
    }
  ]
}