{
  "meta": {
    "identifier": "Disintegrator cannon",
    "prevIdentifier": "Dark Lance - 218"
  },
  "selectionEntries": [
    {
      "costs": [
        {
          "name": "pts",
          "costTypeId": "points",
          "value": 30.0
        },
        {
          "name": " PL",
          "costTypeId": "e356-c769-5920-6e14"
        }
      ],
      "constraints": [
        {
          "id": "2917-ae7e-89eb-0364",
          "type": 1,
          "field": "selections",
          "scope": "parent",
          "value": 1.0
        }
      ],
      "id": "dd11-f611-6a44-18ae",
      "name": "Disintegrator cannon",
      "page": "0",
      "infoLinks": [
        {
          "targetId": "93b7-713e-41f8-a4b8",
          "id": "4b8b-bc8b-9381-7207",
          "name": "Disintegrator cannon"
        }
      ]
    }
  ]
}