{
  "meta": {
    "identifier": "The Spartean",
    "prevIdentifier": "The Crusader's Helm"
  },
  "selectionEntries": [
    {
      "costs": [
        {
          "name": " PL",
          "costTypeId": "e356-c769-5920-6e14"
        },
        {
          "name": "pts",
          "costTypeId": "points"
        }
      ],
      "constraints": [
        {
          "id": "e7c5-9aa6-9108-3ce7",
          "type": 1,
          "field": "selections",
          "scope": "roster",
          "value": 1.0,
          "shared": true,
          "includeChildSelections": true,
          "includeChildForces": true
        }
      ],
      "id": "b157-e12c-7add-a9b9",
      "name": "The Spartean",
      "modifiers": [
        {
          "field": "hidden",
          "value": "true",
          "conditionGroups": [
            {
              "conditions": [
                {
                  "childId": "1ceb-4568-edeb-e155",
                  "type": 3,
                  "field": "selections",
                  "scope": "force",
                  "shared": true,
                  "includeChildSelections": true,
                  "includeChildForces": true
                },
                {
                  "childId": "f878-fe21-2fb2-08e5",
                  "type": 2,
                  "field": "selections",
                  "scope": "force",
                  "shared": true,
                  "includeChildSelections": true,
                  "includeChildForces": true
                }
              ]
            }
          ]
        }
      ]
    }
  ]
}