{
  "meta": {
    "identifier": "Ghost Ark Track 1",
    "prevIdentifier": "Transport Capacity (Ghost Ark)"
  },
  "profiles": [
    {
      "profileTypeId": "9b74-b72b-d6bc-194a",
      "profileTypeName": "Unit Wound Track (Movement/BS/A)",
      "characteristics": [
        {
          "name": "Remaining Wounds",
          "characteristicTypeId": "7b4c-c6b9-4725-d7e2",
          "value": "8-14+"
        },
        {
          "name": "Movement",
          "characteristicTypeId": "51f5-7e11-746d-e649",
          "value": "12\""
        },
        {
          "name": "Ballistic Skill",
          "characteristicTypeId": "aea4-93ca-2bcf-f3cb",
          "value": "3+"
        },
        {
          "name": "Attacks",
          "characteristicTypeId": "919e-ec33-44ab-5051",
          "value": "3"
        }
      ],
      "id": "a0fb-2a05-8ea8-58a7",
      "name": "Ghost Ark Track 1",
      "book": "IA: Xenos"
    }
  ]
}