{
  "meta": {
    "identifier": "Slaughter blade"
  },
  "selectionEntries": [
    {
      "costs": [
        {
          "name": " PL",
          "costTypeId": "e356-c769-5920-6e14"
        },
        {
          "name": "pts",
          "costTypeId": "points"
        }
      ],
      "constraints": [
        {
          "id": "0ff1-aaff-e01f-89f7",
          "type": 1,
          "field": "selections",
          "scope": "parent",
          "value": 1.0
        },
        {
          "id": "6f9a-70f8-061a-965f",
          "field": "selections",
          "scope": "parent",
          "value": 1.0
        }
      ],
      "id": "26d0-a39e-91c6-2689",
      "name": "Slaughter blade"
    }
  ]
}