{
  "meta": {
    "identifier": "Bane of Monstrosities",
    "prevIdentifier": "Librarian with Jump Pack"
  },
  "selectionEntries": [
    {
      "costs": [
        {
          "name": " PL",
          "costTypeId": "e356-c769-5920-6e14"
        },
        {
          "name": "pts",
          "costTypeId": "points"
        }
      ],
      "constraints": [
        {
          "id": "4243-f0a1-c3d7-4330",
          "type": 1,
          "field": "selections",
          "scope": "parent",
          "value": 1.0,
          "shared": true
        }
      ],
      "id": "ec5e-133b-3e38-eeeb",
      "name": "Bane of Monstrosities"
    }
  ]
}