{
  "meta": {
    "identifier": "Tesseract Vault"
  },
  "selectionEntries": [
    {
      "type": 1,
      "costs": [
        {
          "name": " PL",
          "costTypeId": "e356-c769-5920-6e14",
          "value": 24.0
        },
        {
          "name": "pts",
          "costTypeId": "points",
          "value": 496.0
        }
      ],
      "categoryLinks": [
        {
          "targetId": "6a37-4c9f-a323-a8f2",
          "id": "b243-f93c-c0f8-6f99",
          "name": "",
          "book": "Index: Xenos 1"
        },
        {
          "targetId": "f9fc-440b-8d07-a569",
          "id": "3a70-8364-0a4d-5b43",
          "name": "",
          "book": "Index: Xenos 1"
        },
        {
          "targetId": "876e-ea78-1fdf-f250",
          "id": "a8e6-5eb3-e4b2-2d51",
          "name": "",
          "book": "Index: Xenos 1"
        },
        {
          "targetId": "3117-16d8-fcef-4f56",
          "id": "4c67-1b6c-8917-c98e",
          "name": "",
          "book": "Index: Xenos 1"
        },
        {
          "targetId": "23c9-73a1-47bb-2416",
          "id": "52d7-d813-1ea0-d435",
          "name": "",
          "book": "Index: Xenos 1"
        },
        {
          "targetId": "bdda-36f0-4f32-1639",
          "id": "728d-b913-498e-b365",
          "name": "",
          "book": "Index: Xenos 1"
        },
        {
          "targetId": "c8fd-783f-3230-493e",
          "id": "836d-09b8-5696-a01d",
          "name": "",
          "book": "Index: Xenos 1"
        }
      ],
      "entryLinks": [
        {
          "constraints": [
            {
              "id": "e21c-039c-4098-40d6",
              "type": 1,
              "field": "selections",
              "scope": "parent",
              "value": 1.0,
              "shared": true
            },
            {
              "id": "9d02-6028-a97d-1f70",
              "field": "selections",
              "scope": "parent",
              "value": 1.0,
              "shared": true
            }
          ],
          "targetId": "d642-3923-dc26-9bdb",
          "id": "2c4d-39bd-c000-daf1",
          "name": "",
          "book": "Index: Xenos 1"
        },
        {
          "constraints": [
            {
              "id": "3721-bad1-9f8d-2adb",
              "type": 1,
              "field": "selections",
              "scope": "parent",
              "value": 4.0,
              "shared": true
            },
            {
              "id": "d9fa-20bb-a116-4300",
              "field": "selections",
              "scope": "parent",
              "value": 4.0,
              "shared": true
            }
          ],
          "targetId": "7f44-2a1f-a127-3e29",
          "id": "94ca-1753-849b-84dc",
          "name": "",
          "book": "Index: Xenos 1"
        },
        {
          "constraints": [
            {
              "id": "6bda-87a8-5425-bb48",
              "type": 1,
              "field": "selections",
              "scope": "parent",
              "value": 1.0,
              "shared": true
            },
            {
              "id": "465c-c529-d807-9c60",
              "field": "selections",
              "scope": "parent",
              "value": 1.0,
              "shared": true
            }
          ],
          "targetId": "496d-33f1-f9e5-bade",
          "id": "bfb5-9fda-5aa7-03aa",
          "name": "",
          "book": "Index: Xenos 1"
        },
        {
          "constraints": [
            {
              "id": "7aa6-703a-9f2c-0910",
              "type": 1,
              "field": "selections",
              "scope": "parent",
              "value": 1.0,
              "shared": true
            },
            {
              "id": "380d-885a-b880-4b05",
              "field": "selections",
              "scope": "parent",
              "value": 1.0,
              "shared": true
            }
          ],
          "targetId": "5491-9b3d-aa47-4825",
          "id": "40e7-feee-c772-56b6",
          "name": "",
          "book": "Index: Xenos 1"
        }
      ],
      "id": "e151-00eb-70a6-86b4",
      "name": "Tesseract Vault",
      "book": "Index: Xenos 1"
    }
  ]
}