{
  "meta": {
    "identifier": "Cyclone Missile Launcher and Storm Bolter",
    "prevIdentifier": "Power Fist, Storm Bolter and Meltagun"
  },
  "selectionEntries": [
    {
      "costs": [
        {
          "name": " PL",
          "costTypeId": "e356-c769-5920-6e14"
        },
        {
          "name": "pts",
          "costTypeId": "points"
        }
      ],
      "entryLinks": [
        {
          "constraints": [
            {
              "id": "f549-fca3-1976-6fc7",
              "field": "selections",
              "scope": "parent",
              "value": 1.0,
              "shared": true
            },
            {
              "id": "3d91-35c4-2884-d379",
              "type": 1,
              "field": "selections",
              "scope": "parent",
              "value": 1.0,
              "shared": true
            }
          ],
          "targetId": "2b03-8d64-3711-f300",
          "id": "7d9a-122c-fdf3-db3f",
          "name": "New EntryLink"
        },
        {
          "constraints": [
            {
              "id": "5d64-147f-9b84-dde1",
              "field": "selections",
              "scope": "parent",
              "value": 1.0,
              "shared": true
            },
            {
              "id": "65bb-020c-3557-f9f0",
              "type": 1,
              "field": "selections",
              "scope": "parent",
              "value": 1.0,
              "shared": true
            }
          ],
          "targetId": "25b3-79f7-73cd-9321",
          "id": "21cf-377f-cbdf-f16e",
          "name": "New EntryLink"
        }
      ],
      "id": "2c57-923c-9e52-6af9",
      "name": "Cyclone Missile Launcher and Storm Bolter"
    }
  ]
}