{
  "meta": {
    "identifier": "Heavy rail rifle",
    "prevIdentifier": "High-output burst cannon"
  },
  "profiles": [
    {
      "profileTypeId": "d5f97c0b-9fc9-478d-aa34-a7c414d3ea48",
      "profileTypeName": "Weapon",
      "characteristics": [
        {
          "name": "Range",
          "characteristicTypeId": "6fa97fa8-ea74-4a27-a0fb-bc4e5f367464",
          "value": "60\""
        },
        {
          "name": "Type",
          "characteristicTypeId": "077c342f-d7b9-45c6-b8af-88e97cafd3a2",
          "value": "Heavy 2"
        },
        {
          "name": "S",
          "characteristicTypeId": "59b1-319e-ec13-d466",
          "value": "8"
        },
        {
          "name": "AP",
          "characteristicTypeId": "75aa-a838-b675-6484",
          "value": "-4"
        },
        {
          "name": "D",
          "characteristicTypeId": "ae8a-3137-d65b-4ca7",
          "value": "D6"
        },
        {
          "name": "Abilities",
          "characteristicTypeId": "837d-5e63-aeb7-1410",
          "value": "For each wound roll of 6+, the target unit suffers a mortal wound in addition to the normal damage."
        }
      ],
      "id": "25da-fd30-ac25-de23",
      "name": "Heavy rail rifle"
    }
  ]
}