{
  "meta": {
    "identifier": "Super-Heavy Detachment"
  },
  "forceEntries": [
    {
      "categoryLinks": [
        {
          "targetId": "ff36a6f3-19bf-4f48-8956-adacfd28fe74",
          "id": "d689-19e3-5f4f-d9e5",
          "name": "No Force Org Slot"
        },
        {
          "targetId": "c888f08a-6cea-4a01-8126-d374a9231554",
          "id": "97d5-c11b-a1c8-2693",
          "name": "Lord of War"
        }
      ],
      "id": "6576-b25c-8ce9-8860",
      "name": "Super-Heavy Detachment"
    }
  ]
}