{
  "meta": {
    "identifier": "Sky-slasher Swarm"
  },
  "selectionEntries": [
    {
      "type": 1,
      "costs": [
        {
          "name": "pts",
          "costTypeId": "points",
          "value": 11.0
        },
        {
          "name": " PL",
          "costTypeId": "e356-c769-5920-6e14"
        }
      ],
      "constraints": [
        {
          "id": "21f2-afe4-1fa4-4655",
          "field": "selections",
          "scope": "parent",
          "value": 3.0,
          "shared": true
        },
        {
          "id": "7ed8-a9ec-7764-b029",
          "type": 1,
          "field": "selections",
          "scope": "parent",
          "value": 9.0,
          "shared": true
        }
      ],
      "entryLinks": [
        {
          "constraints": [
            {
              "id": "98a8-ca76-e182-af12",
              "field": "selections",
              "scope": "parent",
              "value": 1.0,
              "shared": true
            },
            {
              "id": "761e-041e-4888-58c7",
              "type": 1,
              "field": "selections",
              "scope": "parent",
              "value": 1.0,
              "shared": true
            }
          ],
          "targetId": "2634-0525-7b04-6f89",
          "id": "06f1-4e08-3e2a-626b",
          "name": "Claws and Teeth"
        },
        {
          "constraints": [
            {
              "id": "2631-a3eb-8ba1-da28",
              "type": 1,
              "field": "selections",
              "scope": "parent",
              "value": 1.0,
              "shared": true
            }
          ],
          "targetId": "8017-6992-ddd7-5882",
          "id": "e308-bedd-aff9-aac9",
          "name": "Spinemaws"
        }
      ],
      "id": "7fee-5b3c-b0d8-1ab4",
      "name": "Sky-slasher Swarm"
    }
  ]
}