{
  "meta": {
    "identifier": "XV88 Broadside Battlesuits"
  },
  "profiles": [
    {
      "profileTypeId": "b900-0afb-e411-2cbb",
      "profileTypeName": "Keywords",
      "characteristics": [
        {
          "name": "Keywords (Faction)",
          "characteristicTypeId": "6b92-2d97-5144-62bc",
          "value": "T'au Empire, <Sept>"
        },
        {
          "name": "Keywords (Basic)",
          "characteristicTypeId": "ce6c-4765-4bb8-bd49",
          "value": "Battlesuit, XV88 Broadside Battlesuits"
        }
      ],
      "id": "a0c8-2271-3efd-dc90",
      "name": "XV88 Broadside Battlesuits"
    }
  ]
}