{
  "meta": {
    "identifier": "Bolt pistol arm"
  },
  "selectionEntryGroups": [
    {
      "defaultSelectionEntryId": "f96e-1853-0324-b999",
      "constraints": [
        {
          "id": "563d-d37c-5f40-cde2",
          "field": "selections",
          "scope": "parent",
          "value": 1.0,
          "shared": true
        },
        {
          "id": "8d56-59be-4cd3-4cf6",
          "type": 1,
          "field": "selections",
          "scope": "parent",
          "value": 1.0
        }
      ],
      "entryLinks": [
        {
          "constraints": [
            {
              "id": "35b3-c17f-81ee-5847",
              "type": 1,
              "field": "selections",
              "scope": "parent",
              "value": 1.0,
              "shared": true
            }
          ],
          "targetId": "37d3-7098-d596-9948",
          "id": "f96e-1853-0324-b999",
          "name": "Bolt pistol"
        }
      ],
      "id": "b75a-9006-cb6b-b316",
      "name": "Bolt pistol arm"
    }
  ]
}