{
  "meta": {
    "identifier": "Stat Damage - M, WS & BS",
    "prevIdentifier": "Stat Damage - WS, BS & A"
  },
  "profileTypes": [
    {
      "id": "1d35-9cf8-74f1-32c4",
      "name": "Stat Damage - M, WS & BS",
      "characteristicTypes": [
        {
          "id": "b727-51df-e04a-19d7",
          "name": "Remaining W"
        },
        {
          "id": "d77f-9965-665b-2d01",
          "name": "Movement"
        },
        {
          "id": "a29c-7b92-a163-2f4f",
          "name": "WS"
        },
        {
          "id": "dad3-29bb-36d1-1a83",
          "name": "BS"
        }
      ]
    }
  ]
}