{
  "meta": {
    "identifier": "Chaos Lord on Palanquin of Nurgle",
    "prevIdentifier": "Chaos Lord on Juggernaut of Khorne"
  },
  "selectionEntries": [
    {
      "type": 1,
      "costs": [
        {
          "name": "pts",
          "costTypeId": "points",
          "value": 99.0
        },
        {
          "name": " PL",
          "costTypeId": "e356-c769-5920-6e14",
          "value": 6.0
        }
      ],
      "categoryLinks": [
        {
          "isPrimary": true,
          "targetId": "848a6ff2-0def-4c72-8433-ff7da70e6bc7",
          "id": "8741-004e-9a3b-3279",
          "name": "New CategoryLink"
        },
        {
          "targetId": "5cf1-acf2-ca3b-c2e5",
          "id": "ea61-1132-ef93-985d",
          "name": "New CategoryLink"
        },
        {
          "targetId": "eb55-bd6b-3e75-d505",
          "id": "8587-74ee-4e3f-57dd",
          "name": "New CategoryLink"
        },
        {
          "targetId": "ef18-746a-369f-43a4",
          "id": "f4fd-c024-130a-50c6",
          "name": "New CategoryLink"
        },
        {
          "targetId": "0bc5-6451-5612-4a25",
          "id": "f9a2-1233-3fcf-8fe5",
          "name": "New CategoryLink"
        },
        {
          "targetId": "ca10-a5dd-f54f-0ed5",
          "id": "b1ba-926b-0f64-2b53",
          "name": "New CategoryLink"
        },
        {
          "targetId": "0fb6-fcaf-b180-5dda",
          "id": "94ca-6190-3197-05bb",
          "name": "New CategoryLink"
        },
        {
          "targetId": "ad01-caec-17d9-cb8d",
          "id": "264b-7718-3baa-b861",
          "name": "New CategoryLink"
        },
        {
          "targetId": "b2b6-8e4a-9c74-cc37",
          "id": "cb1e-313f-e67c-7e95",
          "name": "New CategoryLink"
        }
      ],
      "entryLinks": [
        {
          "constraints": [
            {
              "id": "ac1f-a3be-6190-cfa1",
              "type": 1,
              "field": "selections",
              "scope": "parent",
              "value": 1.0,
              "shared": true
            },
            {
              "id": "e5e4-a5ee-34b9-aa88",
              "field": "selections",
              "scope": "parent",
              "value": 1.0,
              "shared": true
            }
          ],
          "targetId": "cddf-945e-1335-e681",
          "id": "a304-c216-38f6-663e",
          "name": "Frag & Krak grenades"
        },
        {
          "type": 1,
          "targetId": "383d-d974-00a3-bd09",
          "id": "bbbb-1ab9-6a81-2fae",
          "name": "Chaos Lord Weapon options"
        },
        {
          "type": 1,
          "targetId": "5876-fcc5-8283-1aca",
          "id": "12dd-b1f3-a7a3-45f0",
          "name": "Artefacts of Chaos"
        },
        {
          "constraints": [
            {
              "id": "5cc6-bb17-619e-99c2",
              "type": 1,
              "field": "selections",
              "scope": "parent",
              "value": 1.0,
              "shared": true
            }
          ],
          "targetId": "398a-c8da-c8bd-da58",
          "id": "4da5-3df2-03d5-aaa7",
          "name": "Warlord"
        },
        {
          "type": 1,
          "targetId": "b34c-6c4b-d22c-25b5",
          "id": "0a48-9a93-5a49-5740",
          "name": "Warlord Traits"
        }
      ],
      "id": "e9b8-3691-eed5-b0c7",
      "name": "Chaos Lord on Palanquin of Nurgle",
      "page": "0",
      "infoLinks": [
        {
          "targetId": "c237-7aca-a961-6c59",
          "id": "3714-95b3-8aba-37b4",
          "name": "Sigil of Corruption"
        },
        {
          "targetId": "37a4-1d84-4ef0-c4f6",
          "id": "61bb-67f7-e7e0-7a3c",
          "name": "Death to the False Emperor"
        }
      ]
    }
  ]
}