{
  "meta": {
    "identifier": "Stronghold Assault Defender"
  },
  "forceEntries": [
    {
      "categoryLinks": [
        {
          "targetId": "ff36a6f3-19bf-4f48-8956-adacfd28fe74",
          "id": "3547-81af-f102-632e",
          "name": "No Force Org Slot"
        },
        {
          "targetId": "848a6ff2-0def-4c72-8433-ff7da70e6bc7",
          "id": "0e3c-008f-7e8a-3f6d",
          "name": "HQ"
        },
        {
          "targetId": "5d76b6f5-20ae-4d70-8f59-ade72a2add3a",
          "id": "aaf4-ea80-63a1-328b",
          "name": "Troops"
        },
        {
          "targetId": "638d74c6-bd97-4de5-b65a-6aaa24e9f4b2",
          "id": "1e95-c712-47b6-ebbd",
          "name": "Elites"
        },
        {
          "targetId": "c274d0b0-5866-44bc-9810-91c136ae7438",
          "id": "0f0d-d815-436c-8775",
          "name": "Fast Attack"
        },
        {
          "targetId": "abf5fd55-9ac7-4263-8bc1-a9fb0a8fa6a6",
          "id": "bd09-2ffc-fe1a-508c",
          "name": "Heavy Support"
        },
        {
          "targetId": "e888-1504-aa61-95ff",
          "id": "311d-4ffb-0807-9e37",
          "name": "Flyer"
        },
        {
          "targetId": "d713cda3-5d0f-40d8-b621-69233263ec2a",
          "id": "3fcb-1ea2-66d6-c8bb",
          "name": "Fortification"
        },
        {
          "targetId": "1b66-3f5f-6705-079a",
          "id": "607f-451f-4b13-2410",
          "name": "Dedicated Transport"
        }
      ],
      "id": "bfc9-d668-8dec-a0ee",
      "name": "Stronghold Assault Defender"
    }
  ]
}